README.md
setup.py
pulumi_google_native/__init__.py
pulumi_google_native/_utilities.py
pulumi_google_native/provider.py
pulumi_google_native/pulumi-plugin.json
pulumi_google_native/py.typed
pulumi_google_native.egg-info/PKG-INFO
pulumi_google_native.egg-info/SOURCES.txt
pulumi_google_native.egg-info/dependency_links.txt
pulumi_google_native.egg-info/not-zip-safe
pulumi_google_native.egg-info/requires.txt
pulumi_google_native.egg-info/top_level.txt
pulumi_google_native/accesscontextmanager/__init__.py
pulumi_google_native/accesscontextmanager/v1/__init__.py
pulumi_google_native/accesscontextmanager/v1/_enums.py
pulumi_google_native/accesscontextmanager/v1/_inputs.py
pulumi_google_native/accesscontextmanager/v1/access_level.py
pulumi_google_native/accesscontextmanager/v1/access_policy.py
pulumi_google_native/accesscontextmanager/v1/access_policy_iam_policy.py
pulumi_google_native/accesscontextmanager/v1/gcp_user_access_binding.py
pulumi_google_native/accesscontextmanager/v1/get_access_level.py
pulumi_google_native/accesscontextmanager/v1/get_access_policy.py
pulumi_google_native/accesscontextmanager/v1/get_access_policy_iam_policy.py
pulumi_google_native/accesscontextmanager/v1/get_gcp_user_access_binding.py
pulumi_google_native/accesscontextmanager/v1/get_service_perimeter.py
pulumi_google_native/accesscontextmanager/v1/outputs.py
pulumi_google_native/accesscontextmanager/v1/service_perimeter.py
pulumi_google_native/accesscontextmanager/v1beta/__init__.py
pulumi_google_native/accesscontextmanager/v1beta/_enums.py
pulumi_google_native/accesscontextmanager/v1beta/_inputs.py
pulumi_google_native/accesscontextmanager/v1beta/access_level.py
pulumi_google_native/accesscontextmanager/v1beta/access_policy.py
pulumi_google_native/accesscontextmanager/v1beta/get_access_level.py
pulumi_google_native/accesscontextmanager/v1beta/get_access_policy.py
pulumi_google_native/accesscontextmanager/v1beta/get_service_perimeter.py
pulumi_google_native/accesscontextmanager/v1beta/outputs.py
pulumi_google_native/accesscontextmanager/v1beta/service_perimeter.py
pulumi_google_native/analyticshub/__init__.py
pulumi_google_native/analyticshub/v1beta1/__init__.py
pulumi_google_native/analyticshub/v1beta1/_enums.py
