Metadata-Version: 2.1
Name: pulumi-google-native
Version: 0.25.0
Summary: A native Pulumi package for creating and managing Google Cloud resources.
Home-page: https://pulumi.com
License: Apache-2.0
Project-URL: Repository, https://github.com/pulumi/pulumi-google-native
Keywords: pulumi google cloud category/cloud kind/native
Platform: UNKNOWN
